pyodbc_sqlserver/__init__.py
pyodbc_sqlserver/db.py
pyodbc_sqlserver/db_reader.py
pyodbc_sqlserver/db_writer.py
roest1_pyodbc_sqlserver-1.0.3.dist-info/licenses/LICENSE
roest1_pyodbc_sqlserver-1.0.3.dist-info/METADATA
roest1_pyodbc_sqlserver-1.0.3.dist-info/WHEEL
roest1_pyodbc_sqlserver-1.0.3.dist-info/top_level.txt
roest1_pyodbc_sqlserver-1.0.3.dist-info/RECORD
