Metadata-Version: 2.4
Name: roest1-pyodbc-sqlserver
Version: 1.0.3
Summary: Lightweight SQL Server helpers built on pyodbc
Author: Riley Oest
License: MIT License
Requires-Python: >=3.10
License-File: LICENSE
Requires-Dist: pyodbc>=5.0
Requires-Dist: python-dotenv>=1.0
Dynamic: license-file
